{
  "airport": "AEP",
  "updatedAt": "2025-08-24",
  "source": [
    {
      "url": "https://openflights.org/data.php",
      "lastChecked": "2025-08-24",
      "description": "OpenFlights Route Database (Historical)"
    }
  ],
  "carriers": {
    "5Q": {
      "destinations": [
        {
          "iata": "MVD",
          "freq_per_day": null,
          "intl": true,
          "sources": [
            {
              "title": "OpenFlights Route Database",
              "url": "https://openflights.org/data.php"
            }
          ],
          "lastChecked": "2025-08-24"
        },
        {
          "iata": "PDP",
          "freq_per_day": null,
          "intl": true,
          "sources": [
            {
              "title": "OpenFlights Route Database",
              "url": "https://openflights.org/data.php"
            }
          ],
          "lastChecked": "2025-08-24"
        }
      ]
    },
    "8R": {
      "destinations": [
        {
          "iata": "MDQ",
          "freq_per_day": null,
          "intl": true,
          "sources": [
            {
              "title": "OpenFlights Route Database",
              "url": "https://openflights.org/data.php"
            }
          ],
          "lastChecked": "2025-08-24"
        },
        {
          "iata": "PRA",
          "freq_per_day": null,
          "intl": true,
          "sources": [
            {
              "title": "OpenFlights Route Database",
              "url": "https://openflights.org/data.php"
            }
          ],
          "lastChecked": "2025-08-24"
        },
        {
          "iata": "ROS",
          "freq_per_day": null,
          "intl": true,
          "sources": [
            {
              "title": "OpenFlights Route Database",
              "url": "https://openflights.org/data.php"
            }
          ],
          "lastChecked": "2025-08-24"
        },
        {
          "iata": "SFN",
          "freq_per_day": null,
          "intl": true,
          "sources": [
            {
              "title": "OpenFlights Route Database",
              "url": "https://openflights.org/data.php"
            }
          ],
          "lastChecked": "2025-08-24"
        }
      ]
    },
    "AR": {
      "destinations": [
        {
          "iata": "AFA",
          "freq_per_day": null,
          "intl": true,
          "sources": [
            {
              "title": "OpenFlights Route Database",
              "url": "https://openflights.org/data.php"
            }
          ],
          "lastChecked": "2025-08-24",
          "note": "コードシェア"
        },
        {
          "iata": "ASU",
          "freq_per_day": null,
          "intl": true,
          "sources": [
            {
              "title": "OpenFlights Route Database",
              "url": "https://openflights.org/data.php"
            }
          ],
          "lastChecked": "2025-08-24"
        },
        {
          "iata": "BHI",
          "freq_per_day": null,
          "intl": true,
          "sources": [
            {
              "title": "OpenFlights Route Database",
              "url": "https://openflights.org/data.php"
            }
          ],
          "lastChecked": "2025-08-24"
        },
        {
          "iata": "BRC",
          "freq_per_day": null,
          "intl": true,
          "sources": [
            {
              "title": "OpenFlights Route Database",
              "url": "https://openflights.org/data.php"
            }
          ],
          "lastChecked": "2025-08-24"
        },
        {
          "iata": "COR",
          "freq_per_day": null,
          "intl": true,
          "sources": [
            {
              "title": "OpenFlights Route Database",
              "url": "https://openflights.org/data.php"
            }
          ],
          "lastChecked": "2025-08-24"
        },
        {
          "iata": "CPC",
          "freq_per_day": null,
          "intl": true,
          "sources": [
            {
              "title": "OpenFlights Route Database",
              "url": "https://openflights.org/data.php"
            }
          ],
          "lastChecked": "2025-08-24",
          "note": "コードシェア"
        },
        {
          "iata": "CRD",
          "freq_per_day": null,
          "intl": true,
          "sources": [
            {
              "title": "OpenFlights Route Database",
              "url": "https://openflights.org/data.php"
            }
          ],
          "lastChecked": "2025-08-24"
        },
        {
          "iata": "CTC",
          "freq_per_day": null,
          "intl": true,
          "sources": [
            {
              "title": "OpenFlights Route Database",
              "url": "https://openflights.org/data.php"
            }
          ],
          "lastChecked": "2025-08-24",
          "note": "コードシェア"
        },
        {
          "iata": "CWB",
          "freq_per_day": null,
          "intl": true,
          "sources": [
            {
              "title": "OpenFlights Route Database",
              "url": "https://openflights.org/data.php"
            }
          ],
          "lastChecked": "2025-08-24",
          "note": "コードシェア"
        },
        {
          "iata": "EQS",
          "freq_per_day": null,
          "intl": true,
          "sources": [
            {
              "title": "OpenFlights Route Database",
              "url": "https://openflights.org/data.php"
            }
          ],
          "lastChecked": "2025-08-24",
          "note": "コードシェア"
        },
        {
          "iata": "FLN",
          "freq_per_day": null,
          "intl": true,
          "sources": [
            {
              "title": "OpenFlights Route Database",
              "url": "https://openflights.org/data.php"
            }
          ],
          "lastChecked": "2025-08-24"
        },
        {
          "iata": "FMA",
          "freq_per_day": null,
          "intl": true,
          "sources": [
            {
              "title": "OpenFlights Route Database",
              "url": "https://openflights.org/data.php"
            }
          ],
          "lastChecked": "2025-08-24",
          "note": "コードシェア"
        },
        {
          "iata": "FTE",
          "freq_per_day": null,
          "intl": true,
          "sources": [
            {
              "title": "OpenFlights Route Database",
              "url": "https://openflights.org/data.php"
            }
          ],
          "lastChecked": "2025-08-24"
        },
        {
          "iata": "GIG",
          "freq_per_day": null,
          "intl": true,
          "sources": [
            {
              "title": "OpenFlights Route Database",
              "url": "https://openflights.org/data.php"
            }
          ],
          "lastChecked": "2025-08-24"
        },
        {
          "iata": "GRU",
          "freq_per_day": null,
          "intl": true,
          "sources": [
            {
              "title": "OpenFlights Route Database",
              "url": "https://openflights.org/data.php"
            }
          ],
          "lastChecked": "2025-08-24"
        },
        {
          "iata": "IGR",
          "freq_per_day": null,
          "intl": true,
          "sources": [
            {
              "title": "OpenFlights Route Database",
              "url": "https://openflights.org/data.php"
            }
          ],
          "lastChecked": "2025-08-24"
        },
        {
          "iata": "IRJ",
          "freq_per_day": null,
          "intl": true,
          "sources": [
            {
              "title": "OpenFlights Route Database",
              "url": "https://openflights.org/data.php"
            }
          ],
          "lastChecked": "2025-08-24",
          "note": "コードシェア"
        },
        {
          "iata": "JUJ",
          "freq_per_day": null,
          "intl": true,
          "sources": [
            {
              "title": "OpenFlights Route Database",
              "url": "https://openflights.org/data.php"
            }
          ],
          "lastChecked": "2025-08-24"
        },
        {
          "iata": "LUQ",
          "freq_per_day": null,
          "intl": true,
          "sources": [
            {
              "title": "OpenFlights Route Database",
              "url": "https://openflights.org/data.php"
            }
          ],
          "lastChecked": "2025-08-24",
          "note": "コードシェア"
        },
        {
          "iata": "MDQ",
          "freq_per_day": null,
          "intl": true,
          "sources": [
            {
              "title": "OpenFlights Route Database",
              "url": "https://openflights.org/data.php"
            }
          ],
          "lastChecked": "2025-08-24"
        },
        {
          "iata": "MDZ",
          "freq_per_day": null,
          "intl": true,
          "sources": [
            {
              "title": "OpenFlights Route Database",
              "url": "https://openflights.org/data.php"
            }
          ],
          "lastChecked": "2025-08-24"
        },
        {
          "iata": "MVD",
          "freq_per_day": null,
          "intl": true,
          "sources": [
            {
              "title": "OpenFlights Route Database",
              "url": "https://openflights.org/data.php"
            }
          ],
          "lastChecked": "2025-08-24"
        },
        {
          "iata": "NQN",
          "freq_per_day": null,
          "intl": true,
          "sources": [
            {
              "title": "OpenFlights Route Database",
              "url": "https://openflights.org/data.php"
            }
          ],
          "lastChecked": "2025-08-24"
        },
        {
          "iata": "PDP",
          "freq_per_day": null,
          "intl": true,
          "sources": [
            {
              "title": "OpenFlights Route Database",
              "url": "https://openflights.org/data.php"
            }
          ],
          "lastChecked": "2025-08-24",
          "note": "コードシェア"
        },
        {
          "iata": "POA",
          "freq_per_day": null,
          "intl": true,
          "sources": [
            {
              "title": "OpenFlights Route Database",
              "url": "https://openflights.org/data.php"
            }
          ],
          "lastChecked": "2025-08-24"
        },
        {
          "iata": "PRA",
          "freq_per_day": null,
          "intl": true,
          "sources": [
            {
              "title": "OpenFlights Route Database",
              "url": "https://openflights.org/data.php"
            }
          ],
          "lastChecked": "2025-08-24",
          "note": "コードシェア"
        },
        {
          "iata": "PSS",
          "freq_per_day": null,
          "intl": true,
          "sources": [
            {
              "title": "OpenFlights Route Database",
              "url": "https://openflights.org/data.php"
            }
          ],
          "lastChecked": "2025-08-24"
        },
        {
          "iata": "REL",
          "freq_per_day": null,
          "intl": true,
          "sources": [
            {
              "title": "OpenFlights Route Database",
              "url": "https://openflights.org/data.php"
            }
          ],
          "lastChecked": "2025-08-24"
        },
        {
          "iata": "RES",
          "freq_per_day": null,
          "intl": true,
          "sources": [
            {
              "title": "OpenFlights Route Database",
              "url": "https://openflights.org/data.php"
            }
          ],
          "lastChecked": "2025-08-24"
        },
        {
          "iata": "RGA",
          "freq_per_day": null,
          "intl": true,
          "sources": [
            {
              "title": "OpenFlights Route Database",
              "url": "https://openflights.org/data.php"
            }
          ],
          "lastChecked": "2025-08-24"
        },
        {
          "iata": "RGL",
          "freq_per_day": null,
          "intl": true,
          "sources": [
            {
              "title": "OpenFlights Route Database",
              "url": "https://openflights.org/data.php"
            }
          ],
          "lastChecked": "2025-08-24"
        },
        {
          "iata": "RHD",
          "freq_per_day": null,
          "intl": true,
          "sources": [
            {
              "title": "OpenFlights Route Database",
              "url": "https://openflights.org/data.php"
            }
          ],
          "lastChecked": "2025-08-24",
          "note": "コードシェア"
        },
        {
          "iata": "ROS",
          "freq_per_day": null,
          "intl": true,
          "sources": [
            {
              "title": "OpenFlights Route Database",
              "url": "https://openflights.org/data.php"
            }
          ],
          "lastChecked": "2025-08-24",
          "note": "コードシェア"
        },
        {
          "iata": "RSA",
          "freq_per_day": null,
          "intl": true,
          "sources": [
            {
              "title": "OpenFlights Route Database",
              "url": "https://openflights.org/data.php"
            }
          ],
          "lastChecked": "2025-08-24",
          "note": "コードシェア"
        },
        {
          "iata": "SCL",
          "freq_per_day": null,
          "intl": true,
          "sources": [
            {
              "title": "OpenFlights Route Database",
              "url": "https://openflights.org/data.php"
            }
          ],
          "lastChecked": "2025-08-24"
        },
        {
          "iata": "SDE",
          "freq_per_day": null,
          "intl": true,
          "sources": [
            {
              "title": "OpenFlights Route Database",
              "url": "https://openflights.org/data.php"
            }
          ],
          "lastChecked": "2025-08-24"
        },
        {
          "iata": "SFN",
          "freq_per_day": null,
          "intl": true,
          "sources": [
            {
              "title": "OpenFlights Route Database",
              "url": "https://openflights.org/data.php"
            }
          ],
          "lastChecked": "2025-08-24",
          "note": "コードシェア"
        },
        {
          "iata": "SLA",
          "freq_per_day": null,
          "intl": true,
          "sources": [
            {
              "title": "OpenFlights Route Database",
              "url": "https://openflights.org/data.php"
            }
          ],
          "lastChecked": "2025-08-24"
        },
        {
          "iata": "TUC",
          "freq_per_day": null,
          "intl": true,
          "sources": [
            {
              "title": "OpenFlights Route Database",
              "url": "https://openflights.org/data.php"
            }
          ],
          "lastChecked": "2025-08-24"
        },
        {
          "iata": "UAQ",
          "freq_per_day": null,
          "intl": true,
          "sources": [
            {
              "title": "OpenFlights Route Database",
              "url": "https://openflights.org/data.php"
            }
          ],
          "lastChecked": "2025-08-24"
        },
        {
          "iata": "USH",
          "freq_per_day": null,
          "intl": true,
          "sources": [
            {
              "title": "OpenFlights Route Database",
              "url": "https://openflights.org/data.php"
            }
          ],
          "lastChecked": "2025-08-24"
        },
        {
          "iata": "VDM",
          "freq_per_day": null,
          "intl": true,
          "sources": [
            {
              "title": "OpenFlights Route Database",
              "url": "https://openflights.org/data.php"
            }
          ],
          "lastChecked": "2025-08-24",
          "note": "コードシェア"
        }
      ]
    },
    "G3": {
      "destinations": [
        {
          "iata": "GRU",
          "freq_per_day": null,
          "intl": true,
          "sources": [
            {
              "title": "OpenFlights Route Database",
              "url": "https://openflights.org/data.php"
            }
          ],
          "lastChecked": "2025-08-24"
        }
      ]
    },
    "JJ": {
      "destinations": [
        {
          "iata": "GRU",
          "freq_per_day": null,
          "intl": true,
          "sources": [
            {
              "title": "OpenFlights Route Database",
              "url": "https://openflights.org/data.php"
            }
          ],
          "lastChecked": "2025-08-24"
        }
      ]
    },
    "LA": {
      "destinations": [
        {
          "iata": "BHI",
          "freq_per_day": null,
          "intl": true,
          "sources": [
            {
              "title": "OpenFlights Route Database",
              "url": "https://openflights.org/data.php"
            }
          ],
          "lastChecked": "2025-08-24",
          "note": "コードシェア"
        },
        {
          "iata": "BRC",
          "freq_per_day": null,
          "intl": true,
          "sources": [
            {
              "title": "OpenFlights Route Database",
              "url": "https://openflights.org/data.php"
            }
          ],
          "lastChecked": "2025-08-24"
        },
        {
          "iata": "COR",
          "freq_per_day": null,
          "intl": true,
          "sources": [
            {
              "title": "OpenFlights Route Database",
              "url": "https://openflights.org/data.php"
            }
          ],
          "lastChecked": "2025-08-24",
          "note": "コードシェア"
        },
        {
          "iata": "CRD",
          "freq_per_day": null,
          "intl": true,
          "sources": [
            {
              "title": "OpenFlights Route Database",
              "url": "https://openflights.org/data.php"
            }
          ],
          "lastChecked": "2025-08-24",
          "note": "コードシェア"
        },
        {
          "iata": "IGR",
          "freq_per_day": null,
          "intl": true,
          "sources": [
            {
              "title": "OpenFlights Route Database",
              "url": "https://openflights.org/data.php"
            }
          ],
          "lastChecked": "2025-08-24"
        },
        {
          "iata": "MDZ",
          "freq_per_day": null,
          "intl": true,
          "sources": [
            {
              "title": "OpenFlights Route Database",
              "url": "https://openflights.org/data.php"
            }
          ],
          "lastChecked": "2025-08-24"
        },
        {
          "iata": "NQN",
          "freq_per_day": null,
          "intl": true,
          "sources": [
            {
              "title": "OpenFlights Route Database",
              "url": "https://openflights.org/data.php"
            }
          ],
          "lastChecked": "2025-08-24",
          "note": "コードシェア"
        },
        {
          "iata": "RGL",
          "freq_per_day": null,
          "intl": true,
          "sources": [
            {
              "title": "OpenFlights Route Database",
              "url": "https://openflights.org/data.php"
            }
          ],
          "lastChecked": "2025-08-24",
          "note": "コードシェア"
        },
        {
          "iata": "SCL",
          "freq_per_day": null,
          "intl": true,
          "sources": [
            {
              "title": "OpenFlights Route Database",
              "url": "https://openflights.org/data.php"
            }
          ],
          "lastChecked": "2025-08-24"
        },
        {
          "iata": "SLA",
          "freq_per_day": null,
          "intl": true,
          "sources": [
            {
              "title": "OpenFlights Route Database",
              "url": "https://openflights.org/data.php"
            }
          ],
          "lastChecked": "2025-08-24"
        },
        {
          "iata": "TUC",
          "freq_per_day": null,
          "intl": true,
          "sources": [
            {
              "title": "OpenFlights Route Database",
              "url": "https://openflights.org/data.php"
            }
          ],
          "lastChecked": "2025-08-24"
        },
        {
          "iata": "UAQ",
          "freq_per_day": null,
          "intl": true,
          "sources": [
            {
              "title": "OpenFlights Route Database",
              "url": "https://openflights.org/data.php"
            }
          ],
          "lastChecked": "2025-08-24"
        },
        {
          "iata": "USH",
          "freq_per_day": null,
          "intl": true,
          "sources": [
            {
              "title": "OpenFlights Route Database",
              "url": "https://openflights.org/data.php"
            }
          ],
          "lastChecked": "2025-08-24",
          "note": "コードシェア"
        }
      ]
    },
    "OY": {
      "destinations": [
        {
          "iata": "PMY",
          "freq_per_day": null,
          "intl": true,
          "sources": [
            {
              "title": "OpenFlights Route Database",
              "url": "https://openflights.org/data.php"
            }
          ],
          "lastChecked": "2025-08-24"
        },
        {
          "iata": "SLA",
          "freq_per_day": null,
          "intl": true,
          "sources": [
            {
              "title": "OpenFlights Route Database",
              "url": "https://openflights.org/data.php"
            }
          ],
          "lastChecked": "2025-08-24"
        }
      ]
    }
  }
}
